pylicensing/__init__.py
pylicensing/database.py
pylicensing/exceptions.py
pylicensing/hwid_tools.py
pylicensing/validation.py
pylicensing/key/__init__.py
pylicensing/key/_generate.py
pylicensing/key/format.py
pylicensing/key/key.py
pylicensing-0.0.3.dist-info/LICENSE
pylicensing-0.0.3.dist-info/METADATA
pylicensing-0.0.3.dist-info/WHEEL
pylicensing-0.0.3.dist-info/top_level.txt
pylicensing-0.0.3.dist-info/RECORD
