Metadata-Version: 2.1
Name: pylicensing
Version: 0.0.3
Summary: Simple licensing helper using mongodb
Author-email: Kenny Hommel <kennyhommel36@gmail.com>
Project-URL: Homepage, https://github.com/kennyhml/pylicensing
Project-URL: Bug Tracker, https://github.com/kennyhml/pylicensing/issues
Classifier: Programming Language :: Python :: 3
Classifier: License :: OSI Approved :: MIT License
Classifier: Operating System :: OS Independent
Requires-Python: >=3.6
License-File: LICENSE
Requires-Dist: pymongo
Requires-Dist: python-dotenv
Requires-Dist: py-machineid
